BBM-233/project_2/test/dff.v
module dff (
    input D,      // Data input
    input CLK,    // Clock input
    input RESET,  // Asynchronous reset, active high
    output reg Q  // Output
);
    // Your code goes here.  DO NOT change anything that is already given! Otherwise, you will not be able to pass the tests!
endmodule

BBM-233/project_2/templaye/machine_d.v
// M MUSTAFA KARATAŞ
// 2230356164
// BBM_233 Verilog assigment II
module machine_d(
    input wire CLK,     // 
    input wire RESET,   // 
    input wire x,       // x 
    output wire F,       // F 
    output wire [2:0] S  // S 
);

    wire d1_in, d2_in, d3_in;   // D flip-flop inputs
    wire A, B, C;           // flipflopt output wire

    //  define d flip-flopp's input putput
    dff DFF1(.CLK(CLK), .RESET(RESET), .D(d1_in), .Q(A));
    dff DFF2(.CLK(CLK), .RESET(RESET), .D(d2_in), .Q(B));
    dff DFF3(.CLK(CLK), .RESET(RESET), .D(d3_in), .Q(C));

    // D flip-floop 1
    assign d1_in = A | (B & ~x);     
    // D flip-floop 2
    assign d2_in = (B & x) | (~B & ~x) | (A & ~x);      
    // D flip-floop 3
    assign d3_in = (~C & x) | (C & ~x);

    // Output
    assign F = (A & B & ~C);
    // S[0], S[1], S[2] 
    assign S[0] = C;
    assign S[1] = B;
    assign S[2] = A;

endmodule

BBM-233/project_2/templaye/machine_d_tb.v
// M MUSTAFA KARATAŞ
// 2230356164
// BBM_233 Verilog assigment II
module machine_d_tb;
    // Your code goes here.  DO NOT change anything that is already given! Otherwise, you will not be able to pass the tests!
    reg CLK;
    reg RESET;
    reg x;

    wire F;
    wire [2:0] S;

    machine_d UUT (
        .CLK(CLK),
        .RESET(RESET),
        .x(x),
        .F(F),
        .S(S)
    );

    initial begin
        $dumpfile("machine_d_tb.vcd");
        $dumpvars;
        RESET = 1;
        x = 0;
        #20;

        RESET = 0;
        x = 0;
        #30;

        RESET = 1;
        x =1;
        #10;

        RESET = 0;
        #30;

        RESET = 1;
        x =0;
        #10;

        RESET = 0;
        x = 1;
        #10;

        x = 0;
        #40;

        x = 1;
        #10;





        $finish;
    end

    initial begin
        CLK = 1;
        forever begin
            #5;
            CLK = ~CLK;
        end
    end

endmodule

BBM-233/project_2/project_2_vivado/project_2_vivado.sim/sim_1/behav/xsim/counter_d_result.vcd
$date
   Thu Dec 28 14:54:12 2023
$end

$version
  2023.2
  $dumpfile ("counter_d_result.vcd") 
$end

$timescale
  1ps
$end

$scope module machine_d_tb $end
$var reg 1 ! CLK $end
$var reg 1 " RESET $end
$var reg 1 # x $end
$var wire 1 $ F $end
$var wire 3 % S [2:0] $end
$scope module UUT $end
$var wire 1 & CLK $end
$var wire 1 ' RESET $end
$var wire 1 ( x $end
$var wire 1 $ F $end
$var wire 3 % S [2:0] $end
$var wire 1 ) d1_in $end
$var wire 1 * d2_in $end
$var wire 1 + d3_in $end
$var wire 1 , A $end
$var wire 1 - B $end
$var wire 1 . C $end
$scope module DFF1 $end
$var wire 1 ) D $end
$var wire 1 & CLK $end
$var wire 1 ' RESET $end
$var reg 1 / Q $end
$upscope $end
$scope module DFF2 $end
$var wire 1 * D $end
$var wire 1 & CLK $end
$var wire 1 ' RESET $end
$var reg 1 0 Q $end
$upscope $end
$scope module DFF3 $end
$var wire 1 * D $end
$var wire 1 & CLK $end
$var wire 1 ' RESET $end
$var reg 1 1 Q $end
$upscope $end
$upscope $end
$upscope $end
$enddefinitions $end

#0
$dumpvars
0!
1"
0#
0$
b0 %
0&
1'
0(
0)
1*
0+
0,
0-
0.
0/
00
01
$end

#3000
0"
0'

#5000
1!
b110 %
1&
0*
1-
1.
10
11

#9000
1#
1(
1)

#10000
0!
0&

#15000
1!
1$
b1 %
1&
1*
1,
0-
0.
1/
00
01

#20000
0!
0&

#25000
1!
b111 %
1&
1-
1.
10
11

#29000
0#
0$
0(
0)

#30000
0!
0&

#35000
1!
b110 %
1&
0*
0,
0/

#39000
1#
1(
1)

#40000
0!
0&

#45000
1!
1$
b1 %
1&
1*
1,
0-
0.
1/
00
01

#50000
0!
0&

#55000
1!
b111 %
1&
1-
1.
10
11

#59000
0#
0$
0(
0)

#60000
0!
0&

#65000
1!
b110 %
1&
0*
0,
0/

#69000
1#
1(
1)

#70000
0!
0&

#75000
1!
1$
b1 %
1&
1*
1,
0-
0.
1/
00
01

#80000
0!
0&

#85000
1!
b111 %
1&
1-
1.
10
11

#89000
0#
0$
0(
0)

#90000
0!
0&

#95000
1!
b110 %
1&
0*
0,
0/

#100000
0!
0&

#105000
1!
b0 %
1&
1*
0-
0.
00
01

#109000
1#
1$
1(
1)

#110000
0!
0&

#115000
1!
b111 %
1&
1,
1-
1.
1/
10
11

#119000
0#
0$
0(
0)

#120000
0!
0&

#125000
1!
b110 %
1&
0*
0,
0/

#129000
1#
1(
1)

#130000
0!
0&

#135000
1!
1$
b1 %
1&
1*
1,
0-
0.
1/
00
01

#139000
1"
b0 %
1'
0,
0/

#140000
0!
0&

#144000
0"
0'

#145000
1!
b111 %
1&
1,
1-
1.
1/
10
11

#150000
0!
0&

#154000
0#
0$
0(
0)

#155000
1!
b110 %
1&
0*
0,
0/

#160000
0!
0&

#165000
1!
b0 %
1&
1*
0-
0.
00
01

#170000
0!
0&

#175000
1!
b110 %
1&
0*
1-
1.
10
11

#180000
0!
0&

#185000
1!
b0 %
1&
1*
0-
0.
00
01

#190000
0!
0&

#194000
1#
1$
1(
1)

#195000
1!
b111 %
1&
1,
1-
1.
1/
10
11

#200000
0!
0&

#204000
1"
b0 %
1'
0,
0-
0.
0/
00
01

