BBM-233/project_2/templaye/jkff.v
// M MUSTAFA KARATAŞ
// 2230356164
// BBM_233 Verilog assigment II
module jkff (
    input J,      // Data input
    input K,      // Data input
    input CLK,    // Clock input
    input RESET,  // Asynchronous reset, active high
    output reg Q  // Output
);
    // Your code goes here.  DO NOT change anything that is already given! Otherwise, you will not be able to pass the tests!
    // JK flip-flop 
    always @(posedge CLK or posedge RESET) begin
        if (RESET) begin
            Q <= 1'b0; 
        end else begin
            case ({J, K})
                2'b00: Q <= Q; // J=0, K=0 
                2'b01: Q <= 1'b0; // J=0, K=1 
                2'b10: Q <= 1'b1; // J=1, K=0 
                2'b11: Q <= ~Q; // J=1, K=1 
            endcase
        end
    end
endmodule

BBM-233/project_2/templaye/machine_jk.v
// M MUSTAFA KARATAŞ
// 2230356164
// BBM_233 Verilog assigment II
module machine_jk(
    input wire x,
    input wire CLK,
    input wire RESET,
    output wire F,
    output wire [2:0] S
);
    // Your code goes here.  DO NOT change anything that is already given! Otherwise, you will not be able to pass the tests!
    wire j1_in, j2_in, j3_in;
    wire k1_in, k2_in, k3_in;
    wire A,B,C;

    // defene jk flip flops's input/outputs
    jkff JKFF1(.CLK(CLK), .RESET(RESET), .J(j1_in), .K(k1_in), .Q(A));
    jkff JKFF2(.CLK(CLK), .RESET(RESET), .J(j2_in), .K(k2_in), .Q(B));
    jkff JKFF3(.CLK(CLK), .RESET(RESET), .J(j3_in), .K(k3_in), .Q(C));

    // JK flip-floop 1
    assign j1_in = (B & ~x);
    assign k1_in = ~A;  

    // JK flip-floop 2
    assign j2_in = (~B & ~x);
    assign k2_in = (~A & ~x);

    // JK flip-floop 3
    assign j3_in = x;
    assign k3_in = x;

    // output 
    assign F = (A & B & ~C);

    // S[0], S[1], S[2] 
    assign S[0] = C;
    assign S[1] = B;
    assign S[2] = A;

endmodule

BBM-233/project_2/templaye/machine_jk_tb.v
// M MUSTAFA KARATAŞ
// 2230356164
// BBM_233 Verilog assigment II
module machine_jk_tb;
    // Your code goes here.  DO NOT change anything that is already given! Otherwise, you will not be able to pass the tests!
    reg CLK;
    reg RESET;
    reg x;

    wire F;
    wire [2:0] S;

    machine_jk UUT (
        .CLK(CLK),
        .RESET(RESET),
        .x(x),
        .F(F),
        .S(S)
    );

    initial begin
        $dumpfile("machine_d_tb.vcd");
        $dumpvars;
        RESET = 1;
        x = 0;
        #20;

        RESET = 0;
        x = 0;
        #30;

        RESET = 1;
        x =1;
        #10;

        RESET = 0;
        #30;

        RESET = 1;
        x =0;
        #10;

        RESET = 0;
        x = 1;
        #10;

        x = 0;
        #40;

        x = 1;
        #10;

        $finish;
    end

    initial begin
        CLK = 1;
        forever begin
            #5;
            CLK = ~CLK;
        end
    end

endmodule

BBM-233/project_2/project_2_vivado/project_2_vivado.sim/sim_1/behav/xsim/machine_d_tb.vcd
$date
   Tue Jan  2 22:35:07 2024
$end

$version
  2023.2.1
  $dumpfile ("machine_d_tb.vcd") 
$end

$timescale
  1ps
$end

$scope module machine_jk_tb $end
$var reg 1 ! CLK $end
$var reg 1 " RESET $end
$var reg 1 # x $end
$var wire 1 $ F $end
$var wire 3 % S [2:0] $end
$scope module UUT $end
$var wire 1 & x $end
$var wire 1 ' CLK $end
$var wire 1 ( RESET $end
$var wire 1 $ F $end
$var wire 3 % S [2:0] $end
$var wire 1 ) j1_in $end
$var wire 1 * j2_in $end
$var wire 1 + j3_in $end
$var wire 1 , k1_in $end
$var wire 1 - k2_in $end
$var wire 1 . k3_in $end
$var wire 1 / A $end
$var wire 1 0 B $end
$var wire 1 1 C $end
$scope module JKFF1 $end
$var wire 1 ) J $end
$var wire 1 , K $end
$var wire 1 ' CLK $end
$var wire 1 ( RESET $end
$var reg 1 2 Q $end
$upscope $end
$scope module JKFF2 $end
$var wire 1 * J $end
$var wire 1 - K $end
$var wire 1 ' CLK $end
$var wire 1 ( RESET $end
$var reg 1 3 Q $end
$upscope $end
$scope module JKFF3 $end
$var wire 1 + J $end
$var wire 1 . K $end
$var wire 1 ' CLK $end
$var wire 1 ( RESET $end
$var reg 1 4 Q $end
$upscope $end
$upscope $end
$upscope $end
$enddefinitions $end

#0
$dumpvars
1!
1"
0#
0$
b0 %
0&
1'
1(
0)
1*
0+
1,
1-
0.
0/
00
01
02
03
04
$end

#5000
0!
0'

#10000
1!
1'

#15000
0!
0'

#20000
1!
0"
b10 %
1'
0(
1)
0*
10
13

#25000
0!
0'

#30000
1!
b100 %
1'
0)
1*
0,
0-
1/
00
12
03

#35000
0!
0'

#40000
1!
1$
b110 %
1'
1)
0*
10
13

#45000
0!
0'

#50000
1!
1"
1#
0$
b0 %
1&
1'
1(
0)
1+
1,
1.
0/
00
02
03

#55000
0!
0'

#60000
1!
0"
b1 %
1'
0(
11
14

#65000
0!
0'

#70000
1!
b0 %
1'
01
04

#75000
0!
0'

#80000
1!
b1 %
1'
11
14

#85000
0!
0'

#90000
1!
1"
0#
b0 %
0&
1'
1(
1*
0+
1-
0.
01
04

#95000
0!
0'

#100000
1!
0"
1#
b1 %
1&
1'
0(
0*
1+
0-
1.
11
14

#105000
0!
0'

#110000
1!
0#
b11 %
0&
1'
1)
0*
0+
1-
0.
10
13

#115000
0!
0'

#120000
1!
b101 %
1'
0)
1*
0,
0-
1/
00
12
03

#125000
0!
0'

#130000
1!
b111 %
1'
1)
0*
10
13

#135000
0!
0'

#140000
1!
1'

#145000
0!
0'

#150000
1!
1#
1$
b110 %
1&
1'
0)
1+
1.
01
04

