BBM-233/project_1/project_1.srcs/sources_1/new/half_adder.v
`timescale 1ns/10ps

module half_adder(
    input A, B,
    output S, C
);
	// Your code goes here.  DO NOT change anything that is already given! Otherwise, you will not be able to pass the tests!
    // find sum
    // xor G1 (S,A,B);
    assign S = A ^ B;
    // find carry
    assign C = A & B;
    // and G2 (C,A,B);

endmodule

BBM-233/project_1/project_1.srcs/sources_1/new/full_adder.v
`timescale 1ns/10ps

module full_adder(
    input A, B, Cin,
    output S, Cout
);
    wire w1,w2,w3;
    half_adder haM1 (A,B,w1,w2);
    half_adder haM2 (w1,Cin,S,w3);
    or G1 (Cout,w2,w3);

endmodule

BBM-233/project_1/project_1.srcs/sim_1/new/full_adder_tb.v
`timescale 1ns/10ps

module full_adder_tb;
    reg A,B,Cin;
    wire S,Cout;
    full_adder UUT (A,B,Cin,S,Cout);
    initial begin
        $dumpfile ("full_adder.vcd");
        $dumpvars;
        A =0;
        B =0;
        Cin =0;
        #10
        A =0;
        B =0;
        Cin =1;
        #10
        A =0;
        B =1;
        Cin =0;
        #10
        A =0;
        B =1;
        Cin =1;
        #10
        A =1;
        B =0;
        Cin =0;
        #10
        A =1;
        B =0;
        Cin =1;
        #10
        A =1;
        B =1;
        Cin =0;
        #10
        A =1;
        B =1;
        Cin =1;
        #10 $finish;
    end

endmodule

BBM-233/project_1/project_1.sim/sim_1/behav/xsim/full_adder.vcd
$date
   Thu Dec  7 00:32:46 2023
$end

$version
  2023.2
  $dumpfile ("full_adder.vcd") 
$end

$timescale
  1ps
$end

$scope module full_adder_tb $end
$var reg 1 ! A $end
$var reg 1 " B $end
$var reg 1 # Cin $end
$var wire 1 $ S $end
$var wire 1 % Cout $end
$scope module UUT $end
$var wire 1 & A $end
$var wire 1 ' B $end
$var wire 1 ( Cin $end
$var wire 1 $ S $end
$var wire 1 % Cout $end
$var wire 1 ) w1 $end
$var wire 1 * w2 $end
$var wire 1 + w3 $end
$scope module haM1 $end
$var wire 1 & A $end
$var wire 1 ' B $end
$var wire 1 ) S $end
$var wire 1 * C $end
$upscope $end
$scope module haM2 $end
$var wire 1 ) A $end
$var wire 1 ( B $end
$var wire 1 $ S $end
$var wire 1 + C $end
$upscope $end
$upscope $end
$upscope $end
$enddefinitions $end

#0
$dumpvars
0!
0"
0#
0$
0%
0&
0'
0(
0)
0*
0+
$end

#10000
1#
1$
1(

#20000
1"
0#
1$
1'
0(
1)

#30000
1#
0$
1%
1(
1+

#40000
1!
0"
0#
1$
0%
1&
0'
0(
0+

#50000
1#
0$
1%
1(
1+

#60000
1"
0#
0$
1'
0(
0)
1*
0+

#70000
1#
1$
1(
