BBM-233/project_1/project_1.srcs/sources_1/new/half_adder.v
`timescale 1ns/10ps

module half_adder(
    input A, B,
    output S, C
);
	// Your code goes here.  DO NOT change anything that is already given! Otherwise, you will not be able to pass the tests!
    // find sum
    // xor G1 (S,A,B);
    assign S = A ^ B;
    // find carry
    assign C = A & B;
    // and G2 (C,A,B);

endmodule

BBM-233/project_1/project_1.srcs/sources_1/new/full_adder.v
`timescale 1ns/10ps

module full_adder(
    input A, B, Cin,
    output S, Cout
);
    wire w1,w2,w3;
    half_adder haM1 (A,B,w1,w2);
    half_adder haM2 (w1,Cin,S,w3);
    or G1 (Cout,w2,w3);

endmodule

BBM-233/project_1/project_1.srcs/sources_1/new/multiplier.v
`timescale 1ns / 1ps

module multiplier(
    input [2:0] A, B,
    output [5:0] P
    );
//    wire w1,w2,w3,w4,w5,w6,w7,w8,w9,w10,w11,w12,w13,w14,w15;
//    and G1_A0andB0  (P[0],A[0],B[0]);
//    and G2_A1andB0  (w1,A[1],B[0]);
//    and G3_A2andB0  (w2,A[2],B[0]);
//    and G4_A0andB1  (w3,A[0],B[1]);
//    and G5_A1andB1  (w4,A[1],B[1]);
//    and G6_A2andB1  (w5,A[2],B[1]);
//    and G7_A0andB2  (w9,A[0],B[1]);
//    and G8_A1andB2  (w10,A[1],B[1]);
//    and G9_A2andB2  (w11,A[2],B[1]);
    wire [2:0] w1,w2,w3;
    wire w6,w7,w8,w12,w13,w14,w15;
    genvar i;
    generate
        for (i = 0; i < 3; i = i + 1) begin : ANDs
            and G_A0andB (w1[i], A[0], B[i]);
            and G_A1andB (w2[i], A[1], B[i]);
            and G_A2andB (w3[i], A[2], B[i]);
        end
    endgenerate
    and g2 (P[0],w1[0],1);

    half_adder M1_haM (w2[0],w1[1],P[1],w6);
    half_adder M2_haM (w2[1],w1[2],w7,w8);

    full_adder M3_faM (w3[0],w7,w6,P[2],w12);
    full_adder M4_faM (w3[1],w2[2],w8,w13,w14);
    
    half_adder M5_haM (w13,w12,P[3],w15);
    full_adder M6_faM (w3[2],w14,w15,P[4],P[5]);
endmodule

BBM-233/project_1/project_1.srcs/sim_1/new/multiplier.v
`timescale 1ns/10ps

module multiplier_tb;
    reg [2:0] A;
    reg [2:0] B;
    wire [5:0] P;
    multiplier UUT(A,B,P);
    initial begin
        $dumpfile ("multiplier.vcd");
        $dumpvars;
        A = 3'b000;
        B = 3'b000;
        #10;
        A = 3'b111;
        B = 3'b010;
        #10;
        A = 3'b101;
        B = 3'b001;
        #10;
        A = 3'b010;
        B = 3'b011;
        #10;
        A = 3'b100;
        B = 3'b100;
        #10;
        A = 3'b010;
        B = 3'b101;
        #10;
        A = 3'b011;
        B = 3'b100;
        #10;
        A = 3'b100;
        B = 3'b100;
        #10;
        A = 3'b001;
        B = 3'b001;
        #10;
        A = 3'b011;
        B = 3'b110;
        #10;
        A = 3'b111;
        B = 3'b111;
        #10 $finish;
        
    end
endmodule

BBM-233/project_1/project_1.sim/sim_1/behav/xsim/multiplier.vcd
$date
   Sun Dec 10 00:09:59 2023
$end

$version
  2023.2
  $dumpfile ("multiplier.vcd") 
$end

$timescale
  1ps
$end

$scope module multiplier_tb $end
$var reg 3 ! A [2:0] $end
$var reg 3 " B [2:0] $end
$var wire 6 # P [5:0] $end
$scope module UUT $end
$var wire 3 $ A [2:0] $end
$var wire 3 % B [2:0] $end
$var wire 6 # P [5:0] $end
$var wire 3 & w1 [2:0] $end
$var wire 3 ' w2 [2:0] $end
$var wire 3 ( w3 [2:0] $end
$var wire 1 ) w6 $end
$var wire 1 * w7 $end
$var wire 1 + w8 $end
$var wire 1 , w12 $end
$var wire 1 - w13 $end
$var wire 1 . w14 $end
$var wire 1 / w15 $end
$scope module M1_haM $end
$var wire 1 0 A $end
$var wire 1 1 B $end
$var wire 1 2 S $end
$var wire 1 ) C $end
$upscope $end
$scope module M2_haM $end
$var wire 1 3 A $end
$var wire 1 4 B $end
$var wire 1 * S $end
$var wire 1 + C $end
$upscope $end
$scope module M3_faM $end
$var wire 1 5 A $end
$var wire 1 * B $end
$var wire 1 ) Cin $end
$var wire 1 2 S $end
$var wire 1 , Cout $end
$var wire 1 6 w1 $end
$var wire 1 7 w2 $end
$var wire 1 8 w3 $end
$scope module haM1 $end
$var wire 1 5 A $end
$var wire 1 * B $end
$var wire 1 6 S $end
$var wire 1 7 C $end
$upscope $end
$scope module haM2 $end
$var wire 1 6 A $end
$var wire 1 ) B $end
$var wire 1 9 S $end
$var wire 1 8 C $end
$upscope $end
$upscope $end
$scope module M4_faM $end
$var wire 1 : A $end
$var wire 1 ; B $end
$var wire 1 + Cin $end
$var wire 1 - S $end
$var wire 1 . Cout $end
$var wire 1 < w1 $end
$var wire 1 = w2 $end
$var wire 1 > w3 $end
$scope module haM1 $end
$var wire 1 : A $end
$var wire 1 ; B $end
$var wire 1 < S $end
$var wire 1 = C $end
$upscope $end
$scope module haM2 $end
$var wire 1 < A $end
$var wire 1 + B $end
$var wire 1 - S $end
$var wire 1 > C $end
$upscope $end
$upscope $end
$scope module M5_haM $end
$var wire 1 - A $end
$var wire 1 , B $end
$var wire 1 ? S $end
$var wire 1 / C $end
$upscope $end
$scope module M6_faM $end
$var wire 1 @ A $end
$var wire 1 . B $end
$var wire 1 / Cin $end
$var wire 1 A S $end
$var wire 1 B Cout $end
$var wire 1 C w1 $end
$var wire 1 D w2 $end
$var wire 1 E w3 $end
$scope module haM1 $end
$var wire 1 @ A $end
$var wire 1 . B $end
$var wire 1 C S $end
$var wire 1 D C $end
$upscope $end
$scope module haM2 $end
$var wire 1 C A $end
$var wire 1 / B $end
$var wire 1 A S $end
$var wire 1 E C $end
$upscope $end
$upscope $end
$upscope $end
$upscope $end
$enddefinitions $end

#0
$dumpvars
b0 !
b0 "
b0 #
b0 $
b0 %
b0 &
b0 '
b0 (
0)
0*
0+
0,
0-
0.
0/
00
01
02
03
04
05
06
07
08
09
0:
0;
0<
0=
0>
0?
0@
0A
0B
0C
0D
0E
$end

#10000
b111 !
b10 "
b1110 #
b111 $
b10 %
b10 &
b10 '
b10 (
1*
1-
13
16
19
1:
1<
1?

#20000
b101 !
b1 "
b101 #
b101 $
b1 %
b1 &
b0 '
b1 (
0*
0,
0-
11
12
03
15
16
07
19
0:
0<
0?

#30000
b10 !
b11 "
b110 #
b10 $
b11 %
b0 &
b11 '
b0 (
1*
10
01
02
13
05

#40000
b100 !
b100 "
b10000 #
b100 $
b100 %
b0 '
b100 (
0*
00
03
06
09
1@
1A
1C

#50000
b10 !
b101 "
b1010 #
b10 $
b101 %
b101 '
b0 (
1-
10
1;
1<
1?
0@
0A
0C

#60000
b11 !
b100 "
b1100 #
b11 $
b100 %
b100 &
b100 '
1*
00
14
16
19

#70000
b100 !
b10000 #
b100 $
b0 &
b0 '
b100 (
0*
0-
04
06
09
0;
0<
0?
1@
1A
1C

#80000
b1 !
b1 "
b1 #
b1 $
b1 %
b1 &
b0 (
11
12
0@
0A
0C

#90000
b11 !
b110 "
b10010 #
b11 $
b110 %
b110 &
b110 '
1+
1.
01
02
13
14
1;
1<
1>
1A
1C

#100000
b111 !
b111 "
b110001 #
b111 $
b111 %
b111 &
b111 '
b111 (
1)
1,
1-
1/
10
11
12
15
16
18
1:
0<
1=
0>
1@
1A
1B
0C
1D
